{
  "db_name": "PostgreSQL",
  "query": "SELECT id AS \"id: Id<Races>\" FROM races WHERE async_room3 IS NULL AND async_start3 IS NOT NULL AND async_start3 > NOW() AND async_start3 <= NOW() + TIME '00:30:00'",
  "describe": {
    "columns": [
      {
        "ordinal": 0,
        "name": "id: Id<Races>",
        "type_info": "Int8"
      }
    ],
    "parameters": {
      "Left": []
    },
    "nullable": [
      false
    ]
  },
  "hash": "3a45590b7eed33746a4153b0c074ea12d3ede7997bcd3924ab6ac9ce7098347b"
}
